Metadata-Version: 2.1
Name: bitmask26
Version: 0.2.0
Summary: A C++ optimized bitmask implementation with Python bindings
Home-page: https://github.com/adwaithhs/bitmask26
Author: Adwaith H Sivam
Author-email: adwaithhs@gmail.com
Requires-Python: >=3.8
